polars_loess-0.1.1.dist-info/METADATA
polars_loess-0.1.1.dist-info/WHEEL
polars_loess-0.1.1.dist-info/licenses/LICENSE
polars_loess/__init__.py
polars_loess/utils.py
polars_loess/_internal.pyi
polars_loess/_internal.abi3.so
polars_loess-0.1.1.dist-info/RECORD
