Metadata-Version: 2.3
Name: polars-loess
Version: 0.1.1
Classifier: Programming Language :: Rust
Classifier: Programming Language :: Python :: Implementation :: CPython
Classifier: Programming Language :: Python :: Implementation :: PyPy
License-File: LICENSE
Summary: LOESS algorithm for Polars
Keywords: polars,loess,regression,smoothing,data
Author-email: Frank Sauerburger <frank@sauerburger.com>
Requires-Python: >=3.9
Project-URL: Homepage, https://gitlab.sauerburger.com/frank/polars-loess
